README.rst
setup.py
./__init__.py
./package.json
exvar.egg-info/PKG-INFO
exvar.egg-info/SOURCES.txt
exvar.egg-info/dependency_links.txt
exvar.egg-info/entry_points.txt
exvar.egg-info/requires.txt
exvar.egg-info/top_level.txt
exvar.egg-info/zip-safe
src/__init__.py
src/check.py
src/cnst.py
src/error.py
src/exvar.base.yml
src/exvar.yml
src/init.py
src/lib.py
src/ls_dest.py
src/main.py
src/message.py
src/root_path.py
src/run.py