Metadata-Version: 1.0
Name: exvar
Version: 1.2.1
Summary: Local repository specific application configuration management framework.
Home-page: https://github.com/suzuki-shunsuke/exvar.py
Author: Suzuki Shunsuke
Author-email: suzuki.shunsuke.1989@gmail.com
License: MIT
Platform: UNKNOWN
